wagtail_mailchimp_integration-0.2.0.dist-info/licenses/LICENSE
wagtailmailchimp/__init__.py
wagtailmailchimp/admin.py
wagtailmailchimp/api.py
wagtailmailchimp/apps.py
wagtailmailchimp/errors.py
wagtailmailchimp/forms.py
wagtailmailchimp/models.py
wagtailmailchimp/tests.py
wagtailmailchimp/views.py
wagtailmailchimp/wagtail_hooks.py
wagtailmailchimp/widgets.py
wagtailmailchimp/migrations/0001_initial.py
wagtailmailchimp/migrations/__init__.py
wagtailmailchimp/templates/wagtailmailchimp/mailchimp_integration_form.html
wagtailmailchimp/templates/wagtailmailchimp/widgets/audience_select_widget.html
wagtailmailchimp/templates/wagtailmailchimp/widgets/subscriber_optin_widget.html
wagtail_mailchimp_integration-0.2.0.dist-info/METADATA
wagtail_mailchimp_integration-0.2.0.dist-info/WHEEL
wagtail_mailchimp_integration-0.2.0.dist-info/top_level.txt
wagtail_mailchimp_integration-0.2.0.dist-info/RECORD
