Metadata-Version: 2.4
Name: wagtail-mailchimp-integration
Version: 0.2.0
Summary: Integration of Mailchimp Email Marketing in Wagtail Form Builder Pages.
Home-page: https://github.com/wmo-raf/wagtail-mailchimp-integration
Author: Erick Otenyo
Author-email: otenyo.erick@gmail.com
License: MIT
Classifier: Development Status :: 4 - Beta
Classifier: Environment :: Web Environment
Classifier: Intended Audience :: Developers
Classifier: License :: OSI Approved :: MIT License
Classifier: Operating System :: OS Independent
Classifier: Programming Language :: Python :: 3 :: Only
Classifier: Programming Language :: Python :: 3.9
Classifier: Programming Language :: Python :: Implementation :: CPython
Classifier: Topic :: Software Development :: Libraries :: Application Frameworks
Classifier: Topic :: Software Development :: Libraries :: Python Modules
Requires-Python: >=3.9
License-File: LICENSE
Requires-Dist: wagtail>=7.0
Requires-Dist: mailchimp3>=3.0.18
Requires-Dist: django-countries>=7.5.1
Dynamic: license-file
